{"location": "carla:Town07", "agent_density": 5, "random_seed": 407, "agent_states": [{"center": {"x": -102.93, "y": -73.87}, "orientation": 1.57, "speed": 6.86}, {"center": {"x": -51.11, "y": -63.41}, "orientation": 6.26, "speed": 9.21}, {"center": {"x": -82.21, "y": -105.19}, "orientation": 6.24, "speed": 4.86}, {"center": {"x": -57.97, "y": -105.96}, "orientation": 0.04, "speed": 5.8}, {"center": {"x": -73.26, "y": -65.62}, "orientation": 3.13, "speed": 8.69}, {"center": {"x": -182.6, "y": -162.86}, "orientation": 3.18, "speed": 11.01}, {"center": {"x": -132.01, "y": -158.78}, "orientation": 6.28, "speed": 7.95}, {"center": {"x": -171.82, "y": -159.6}, "orientation": 0.03, "speed": 8.66}, {"center": {"x": -144.61, "y": -159.0}, "orientation": 0.04, "speed": 7.91}, {"center": {"x": -149.85, "y": -162.27}, "orientation": 3.15, "speed": 9.59}, {"center": {"x": -168.86, "y": 49.29}, "orientation": 3.12, "speed": 10.52}, {"center": {"x": -131.64, "y": 52.09}, "orientation": 6.27, "speed": 7.69}, {"center": {"x": -151.99, "y": 0.65}, "orientation": 1.59, "speed": 9.95}, {"center": {"x": -152.02, "y": 25.22}, "orientation": 1.6, "speed": 8.73}, {"center": {"x": -128.41, "y": 49.49}, "orientation": 3.12, "speed": 7.46}, {"center": {"x": -0.89, "y": -159.85}, "orientation": 4.72, "speed": 11.67}, {"center": {"x": 49.98, "y": -150.06}, "orientation": 1.1, "speed": 7.79}, {"center": {"x": 38.39, "y": -209.34}, "orientation": 1.46, "speed": 9.18}, {"center": {"x": 40.88, "y": -192.32}, "orientation": 1.51, "speed": 8.87}, {"center": {"x": -0.96, "y": -132.69}, "orientation": 4.72, "speed": 9.77}, {"center": {"x": 25.03, "y": -4.13}, "orientation": 3.15, "speed": 9.51}, {"center": {"x": 54.15, "y": 63.57}, "orientation": 6.26, "speed": 5.96}, {"center": {"x": 15.29, "y": -0.82}, "orientation": 0.05, "speed": 8.27}, {"center": {"x": 49.46, "y": -0.3}, "orientation": 0.06, "speed": 7.47}, {"center": {"x": 56.84, "y": 60.39}, "orientation": 3.01, "speed": 6.31}], "agent_attributes": [{"length": 4.48, "width": 2.13, "rear_axis_offset": 1.7, "agent_type": null, "waypoint": null}, {"length": 4.97, "width": 2.17, "rear_axis_offset": 1.89, "agent_type": null, "waypoint": null}, {"length": 4.58, "width": 2.08, "rear_axis_offset": 1.74, "agent_type": null, "waypoint": null}, {"length": 4.81, "width": 2.15, "rear_axis_offset": 1.83, "agent_type": null, "waypoint": null}, {"length": 4.8, "width": 2.12, "rear_axis_offset": 1.82, "agent_type": null, "waypoint": null}, {"length": 4.43, "width": 2.01, "rear_axis_offset": 1.68, "agent_type": null, "waypoint": null}, {"length": 4.93, "width": 2.14, "rear_axis_offset": 1.87, "agent_type": null, "waypoint": null}, {"length": 4.6, "width": 2.06, "rear_axis_offset": 1.75, "agent_type": null, "waypoint": null}, {"length": 4.62, "width": 2.1, "rear_axis_offset": 1.76, "agent_type": null, "waypoint": null}, {"length": 4.85, "width": 2.08, "rear_axis_offset": 1.84, "agent_type": null, "waypoint": null}, {"length": 4.4, "width": 2.07, "rear_axis_offset": 1.67, "agent_type": null, "waypoint": null}, {"length": 4.6, "width": 2.08, "rear_axis_offset": 1.75, "agent_type": null, "waypoint": null}, {"length": 4.63, "width": 1.97, "rear_axis_offset": 1.76, "agent_type": null, "waypoint": null}, {"length": 5.0, "width": 2.14, "rear_axis_offset": 1.9, "agent_type": null, "waypoint": null}, {"length": 4.82, "width": 2.09, "rear_axis_offset": 1.83, "agent_type": null, "waypoint": null}, {"length": 4.32, "width": 2.07, "rear_axis_offset": 1.64, "agent_type": null, "waypoint": null}, {"length": 4.98, "width": 2.12, "rear_axis_offset": 1.89, "agent_type": null, "waypoint": null}, {"length": 4.64, "width": 2.01, "rear_axis_offset": 1.76, "agent_type": null, "waypoint": null}, {"length": 4.57, "width": 2.03, "rear_axis_offset": 1.74, "agent_type": null, "waypoint": null}, {"length": 4.98, "width": 2.14, "rear_axis_offset": 1.89, "agent_type": null, "waypoint": null}, {"length": 4.55, "width": 2.18, "rear_axis_offset": 1.73, "agent_type": null, "waypoint": null}, {"length": 4.97, "width": 2.23, "rear_axis_offset": 1.89, "agent_type": null, "waypoint": null}, {"length": 4.8, "width": 2.15, "rear_axis_offset": 1.82, "agent_type": null, "waypoint": null}, {"length": 4.67, "width": 2.25, "rear_axis_offset": 1.78, "agent_type": null, "waypoint": null}, {"length": 4.77, "width": 2.16, "rear_axis_offset": 1.81, "agent_type": null, "waypoint": null}], "recurrent_states": [{"packed": [0.011589441448450089, -0.13053077459335327, 0.26288217306137085, -0.22673828899860382, 0.056398920714855194, 0.115438312292099, -0.006155874114483595, -0.0922912135720253, 0.509637176990509, 0.5879689455032349, 0.07091891765594482, -0.16644951701164246, -0.25541064143180847, -0.09713443368673325, -0.032347530126571655, -0.08892035484313965, 0.12408271431922913, 0.16530446708202362, 0.06865609437227249, 0.067533940076828, -0.32797276973724365, -0.3688015937805176, -0.316617876291275, -0.07021192461252213, -0.20302583277225494, -0.654965877532959, -0.2520458996295929, 0.04964815452694893, -0.17284315824508667, 0.1373891979455948, 0.11001640558242798, -0.0573882982134819, 0.18523675203323364, -0.39733177423477173, 0.08035397529602051, 0.04403718560934067, -0.12683363258838654, 0.0066538057290017605, 0.05937166512012482, 0.4649806618690491, 0.11273203790187836, 0.13940098881721497, -0.052177369594573975, 0.02593972533941269, 0.34869545698165894, -0.0027560750022530556, 0.2391268014907837, -0.05394909530878067, 0.012263120152056217, -0.02496989071369171, -0.17839643359184265, 0.0020393552258610725, -0.4580134153366089, 0.021880067884922028, -0.1165032759308815, 0.0011616125702857971, -0.48115628957748413, -0.2868981957435608, -0.09909611940383911, -0.23075561225414276, 0.2012261003255844, -0.17789338529109955, 0.08157078921794891, -0.13646568357944489, -0.17069073021411896, -0.0740681141614914, -0.18058905005455017, 0.4111264646053314, -0.3075513243675232, -0.11874112486839294, -0.04919377714395523, 0.11704032123088837, -0.323228120803833, 0.23115511238574982, 0.040113698691129684, 0.2844240367412567, -0.06317607313394547, -0.2852524220943451, 0.0887608528137207, 0.06597782671451569, 0.3237157166004181, 0.7298431992530823, 0.04315680265426636, 0.23789887130260468, -0.14435744285583496, -0.16149112582206726, -0.06812018156051636, 0.11189836263656616, 0.1753769814968109, -0.07689086347818375, 0.11044305562973022, -0.10020852833986282, 0.12730009853839874, -0.028365856036543846, 0.4097230136394501, 0.02619498409330845, 0.0690506100654602, 0.0361652746796608, -0.45476052165031433, -0.05638240650296211, 0.33069998025894165, -0.036496806889772415, 0.08194497972726822, 0.05770813301205635, 0.24244485795497894, -0.0985061526298523, 0.005102556198835373, 0.05857217311859131, -0.08080799132585526, -0.5183175802230835, 0.4095288813114166, -0.10051517188549042, 0.40439367294311523, -0.5371128916740417, 0.2905822694301605, -0.27689653635025024, -0.35795220732688904, 0.08839664608240128, -0.11245536059141159, 0.3961954414844513, -0.2845180630683899, -0.4781894087791443, 0.034209344536066055, 0.408125102519989, 0.019962197169661522, -0.2712513506412506, 0.05893198773264885, -0.08862977474927902, 102.93414306640625, -73.86993408203125, 1.5703399181365967, 6.859240531921387, -0.14164161682128906, 0.010326743125915527, -1.3815826260810127e-10, -7.884704000815645e-11, 0.024161411449313164, 0.0, 0.0, 0.0, 0.0, 0.024161411449313164, 4.8691519566324e-16, 2.3592239273284576e-16, 0.0, 4.868042343471497e-16, 0.00010100983490701765, -4.87890977618477e-19, 0.0, 2.3592239273284576e-16, -4.87890977618477e-19, 0.00010100983490701765]}, {"packed": [-0.012063566595315933, -0.1467270851135254, -0.39046263694763184, -0.17338524758815765, 0.025404518470168114, 0.09615131467580795, -0.03340505063533783, 0.16860821843147278, 0.024994004517793655, 0.7438703179359436, -0.048356879502534866, 0.17668841779232025, -0.028636708855628967, 0.18030573427677155, 0.20935851335525513, 0.1892767697572708, 0.03929489105939865, 0.21247082948684692, 0.1270829290151596, -0.8129132390022278, -0.00700685940682888, -0.4250442385673523, -0.06743665784597397, 0.02502116560935974, -0.1378307044506073, 0.27848270535469055, 0.07157208025455475, 0.08956565707921982, -0.32451432943344116, 0.08657191693782806, 0.053075388073921204, -0.1290704309940338, 0.174336239695549, 0.1875772625207901, 0.0708959549665451, 0.26125994324684143, -0.0994303748011589, -0.11885754019021988, 0.014449862763285637, 0.09746844321489334, 0.051999662071466446, -0.08782364428043365, -0.10153824836015701, -0.023594625294208527, 0.6243011951446533, -0.40804973244667053, -0.044985752552747726, -0.07772869616746902, 0.06473755836486816, 0.0686555951833725, 0.03393169492483139, 0.09166969358921051, 0.8746413588523865, 0.013409039005637169, -0.04349273070693016, -0.00808474700897932, -0.04078391194343567, -0.04311622679233551, -0.003256562864407897, 0.5231509208679199, 0.025134004652500153, -0.4699252247810364, 0.12606224417686462, 0.015637587755918503, 0.2581205368041992, -0.1482202112674713, 0.23302975296974182, -0.7428227066993713, -0.1816939115524292, -0.11941124498844147, 0.1548917442560196, 0.19545064866542816, 0.31743597984313965, 0.17705148458480835, 0.03815235197544098, 0.278560996055603, 0.07637719810009003, -0.14702105522155762, -0.03195343166589737, -0.12191928178071976, -0.09397011995315552, -0.15558220446109772, -0.28652307391166687, 0.23865720629692078, 0.17524629831314087, 0.07685788720846176, -0.005728647578507662, 0.3909823000431061, -0.6910553574562073, 0.013527615927159786, -0.224885493516922, -0.1198270171880722, 0.08299705386161804, -0.03854033723473549, 0.04298350587487221, 0.06861711293458939, 0.04261580482125282, 0.37107053399086, 0.12275558710098267, 0.07169237732887268, -0.040286608040332794, 0.5713443756103516, 0.21533691883087158, -0.08015558123588562, 0.022859474644064903, 0.09288281202316284, -0.08075545728206635, 0.21122859418392181, 0.2339281588792801, 0.2754177749156952, 0.3473351299762726, -0.059175558388233185, 0.19157856702804565, 0.6399049758911133, -0.032058533281087875, -0.04977273568511009, -0.10486215353012085, 0.06325095146894455, -0.2498760223388672, 0.004905016161501408, -0.6138777136802673, -0.21369569003582, -0.38526514172554016, 0.17418348789215088, -0.0014585525495931506, -0.36092397570610046, 0.3751735985279083, 0.16036063432693481, 51.114959716796875, -63.40686798095703, -3.1173555850982666, 9.213446617126465, -0.08875751495361328, -0.028203248977661133, -1.3815826260810127e-10, -7.884704000815645e-11, 0.024161411449313164, 0.0, 0.0, 0.0, 0.0, 0.02415470965206623, -3.069528138610611e-14, -1.4932499681208355e-14, 0.0, 9.736084686942995e-16, 0.00010100983490701765, -4.87890977618477e-19, 0.0, 4.718447854656915e-16, -4.87890977618477e-19, 0.00010100983490701765]}, {"packed": [0.039608538150787354, 0.04330039024353027, -0.004098351579159498, -0.11505361646413803, 0.04233116656541824, 0.004326581954956055, -0.05454539507627487, 0.0016098810592666268, -0.03572460636496544, 0.8959805369377136, -0.0024190933909267187, 0.41007503867149353, -0.050005823373794556, -0.3532930612564087, -0.4493454694747925, 0.3067813515663147, 0.0070372954942286015, 0.42524439096450806, 0.12131272256374359, -0.5170697569847107, -0.037302982062101364, -0.4922742247581482, 0.030887074768543243, -0.36301395297050476, -0.019098399206995964, -0.23096561431884766, -0.0595821887254715, 0.10329858213663101, -0.5032181143760681, 0.39458659291267395, 0.26890161633491516, -0.09616111218929291, 0.024861708283424377, -0.494437038898468, 0.0437995046377182, 0.045848507434129715, -0.10661090910434723, -0.047782957553863525, 0.04153236001729965, 0.6964388489723206, -0.013932131230831146, -0.05117783695459366, -0.11665264517068863, 0.05383487418293953, 0.6000753045082092, -0.3714238107204437, 0.33371981978416443, -0.13073237240314484, 0.14861750602722168, -0.017786581069231033, -0.4215741455554962, 0.3444563150405884, -0.553150475025177, 0.013042562641203403, -0.3907261788845062, -0.044725555926561356, -0.013741976581513882, -0.11940260976552963, -0.0387507863342762, -0.08586296439170837, -0.10231031477451324, -0.38782405853271484, 0.06723614037036896, -0.16877023875713348, 0.37040308117866516, -0.06158392131328583, 0.032741427421569824, 0.246734619140625, -0.2751583456993103, -0.30087900161743164, 0.13766580820083618, 0.3033367693424225, -0.10135329514741898, 0.18067215383052826, 0.025311917066574097, 0.6086520552635193, 0.05266190320253372, -0.17223061621189117, 0.02820473723113537, -0.06819416582584381, 0.19486559927463531, 0.8096123933792114, -0.29789310693740845, 0.23612487316131592, -0.19346514344215393, 0.24249330163002014, 0.19371666014194489, 0.296967089176178, 0.14913390576839447, -0.016578512266278267, 0.03802144154906273, -0.023549029603600502, 0.018224189057946205, 0.07711131870746613, -0.31668850779533386, 0.07118096947669983, 0.1274423450231552, 0.42015454173088074, -0.34526073932647705, -0.08738134801387787, 0.12792588770389557, 0.09762728214263916, 0.06008608639240265, -0.11354368180036545, 0.04886150360107422, 0.05880999192595482, -0.05464605614542961, 0.21536007523536682, 0.017651192843914032, -0.5034304857254028, 0.6072817444801331, -0.035237520933151245, 0.12084859609603882, -0.2564622461795807, 0.13786521553993225, 0.10608427226543427, 0.2094932198524475, 0.06993262469768524, -0.06452389061450958, 0.611839771270752, -0.3026043176651001, -0.44456401467323303, -0.42423030734062195, 0.1860477328300476, 0.06177328899502754, -0.27357786893844604, 0.18920756876468658, -0.014193701557815075, 82.20811462402344, -105.19025421142578, -3.09712815284729, 4.8607988357543945, 0.00047495588660240173, 0.004339635372161865, -1.3815826260810127e-10, -7.884704000815645e-11, 0.024161411449313164, -3.075057569690287e-14, 1.3000600487637903e-16, 6.591949208711867e-17, -3.0753177782116836e-14, 0.024161411449313164, 2.399881508796664e-16, 1.1796119636642288e-16, 1.2998567608564493e-16, 2.3993267022162125e-16, 0.00010100983490701765, -4.87890977618477e-19, 6.591949208711867e-17, 1.1796119636642288e-16, -4.87890977618477e-19, 0.00010100983490701765]}, {"packed": [-0.02364175394177437, -0.07580390572547913, 0.1435653418302536, -0.28347769379615784, 0.10420004278421402, 0.11866822838783264, -0.18399092555046082, 0.14324183762073517, 0.4626188576221466, 0.7588223218917847, -0.13533002138137817, 0.26611843705177307, -0.11189428716897964, -0.09271921962499619, -0.07677852362394333, 0.42510420083999634, 0.05099688097834587, 0.2109779417514801, 0.15372735261917114, -0.5190587639808655, -0.01801210641860962, -0.7170181274414062, -0.07178452610969543, -0.1886271983385086, -0.2922818958759308, 0.014858493581414223, 0.10203691571950912, 0.08029691874980927, -0.5845110416412354, 0.24803964793682098, 0.1438961923122406, -0.11941370368003845, 0.4207615554332733, -0.07579920440912247, 0.016854779794812202, 0.2626442611217499, -0.10927210003137589, -0.05177808180451393, 0.0671578198671341, 0.5575334429740906, 0.16943807899951935, 0.017490414902567863, -0.1005367711186409, 0.015322043560445309, 0.7836201190948486, -0.04799692705273628, 0.2060895562171936, -0.11686312407255173, 0.027518387883901596, 0.2003188282251358, -0.46533533930778503, 0.3929874300956726, 0.2876027524471283, 0.024331821128726006, -0.1978757232427597, -0.004263903945684433, 0.1392630636692047, -0.07317038625478745, 0.00046566841774620116, -0.04427875578403473, 0.0020430341828614473, -0.7519407272338867, 0.13820131123065948, 0.0005220553721301258, 0.2510627806186676, -0.2011847048997879, -0.005240499973297119, -0.26623424887657166, -0.28327879309654236, -0.06862276047468185, 0.21236547827720642, 0.27910321950912476, 0.16670070588588715, 0.3227039575576782, 0.06491682678461075, 0.5574823021888733, 0.057070787996053696, -0.12991689145565033, -0.011096306145191193, -0.1838158369064331, 0.18607057631015778, 0.40273237228393555, -0.17790643870830536, 0.3263300657272339, -0.04014204815030098, 0.09241148084402084, 0.11929376423358917, 0.44760361313819885, -0.244841068983078, -0.019761977717280388, 0.025659555569291115, -0.08140229433774948, 0.048634715378284454, 0.02957885153591633, -0.008677336387336254, 0.10132184624671936, 0.06454398483037949, 0.5059685707092285, -0.13902470469474792, -0.06755207479000092, 0.16243672370910645, 0.4506419897079468, 0.14006619155406952, -0.09353592991828918, 0.027680449187755585, 0.05875900387763977, -0.05824398249387741, 0.27460145950317383, -0.02968006394803524, -0.12409962713718414, 0.5209704041481018, -0.11459977924823761, 0.40789178013801575, 0.36349043250083923, 0.025563403964042664, -0.10158854722976685, 0.08316311240196228, 0.06590208411216736, -0.16216520965099335, 0.4156130850315094, -0.2966827154159546, -0.3657446801662445, -0.38768470287323, 0.21413400769233704, 0.023622384294867516, -0.1827246993780136, 0.26556676626205444, 0.07569698244333267, 57.971771240234375, -105.95673370361328, 3.1056530475616455, 5.802248477935791, -0.16383743286132812, -0.006857335567474365, -1.3815826260810127e-10, -7.884704000815645e-11, 0.02418743260204792, -5.788702850395566e-12, 2.3961735373667636e-14, 1.1546319456101628e-14, -5.504485756091526e-12, 0.024161411449313164, 2.399881508796664e-16, 1.1796119636642288e-16, 2.2631243125174894e-14, 2.3993267022162125e-16, 0.00010100983490701765, -4.87890977618477e-19, 1.0880185641326534e-14, 1.1796119636642288e-16, -4.87890977618477e-19, 0.00010100983490701765]}, {"packed": [-0.007186817470937967, 0.05230230838060379, -0.030348269268870354, -0.18432895839214325, 0.0638803094625473, 0.04127679765224457, -0.10676281154155731, 0.017811041325330734, 0.14499521255493164, 0.8085188865661621, -0.09328009188175201, 0.2975136339664459, -0.06417953968048096, -0.2432544082403183, -0.32959720492362976, 0.3491964638233185, 0.013507857918739319, 0.34423092007637024, 0.16630816459655762, -0.6225740313529968, -0.02691265568137169, -0.5388720035552979, -0.010878901928663254, -0.18752837181091309, 0.03236283361911774, 0.16510458290576935, -0.06967531144618988, 0.11850498616695404, -0.4189254641532898, 0.3226207196712494, 0.21997980773448944, -0.12684917449951172, -0.18035496771335602, -0.23256556689739227, 0.05823465436697006, 0.18993236124515533, -0.08140306919813156, -0.06406018882989883, 0.01477058045566082, 0.5020365715026855, 0.06606605648994446, -0.03019401989877224, -0.12657010555267334, 0.031359683722257614, 0.703166663646698, -0.16206294298171997, 0.35435548424720764, -0.15436343848705292, 0.0911022275686264, 0.03159857913851738, -0.30425912141799927, 0.4162483215332031, 0.189814031124115, 0.01925831101834774, -0.24657583236694336, -0.02256147563457489, 0.17791397869586945, -0.0988803505897522, -0.050412073731422424, 0.1272229254245758, -0.0695764571428299, -0.5808004140853882, 0.09999600052833557, -0.027823101729154587, 0.35753992199897766, -0.16239890456199646, 0.1354474425315857, -0.43512415885925293, -0.22157056629657745, -0.30861297249794006, 0.14033490419387817, 0.31768205761909485, 0.15207011997699738, 0.28720059990882874, 0.03291582688689232, 0.5413652658462524, 0.06132670119404793, -0.11797113716602325, 0.016521772369742393, -0.11771801859140396, 0.0662647932767868, 0.535226583480835, -0.23526236414909363, 0.16561734676361084, -0.0344805009663105, 0.16159480810165405, 0.15327540040016174, 0.3576797544956207, -0.4439548850059509, -0.009020178578794003, 0.03115183860063553, -0.06655541807413101, 0.021969398483633995, 0.05017217993736267, -0.21848003566265106, 0.07775767147541046, 0.0785059779882431, 0.505620002746582, -0.1473037153482437, -0.05801720544695854, 0.11707770824432373, 0.31565961241722107, 0.14674217998981476, -0.1545078456401825, 0.024922547861933708, 0.06123518943786621, -0.06905629485845566, 0.1926247924566269, 0.09318926185369492, -0.24658837914466858, 0.49190598726272583, -0.10224509239196777, 0.21340776979923248, 0.3374168872833252, 0.06292405724525452, 0.042336355894804, 0.13412310183048248, 0.05764193832874298, -0.08300933241844177, 0.4030107259750366, -0.3634307086467743, -0.35313916206359863, -0.5674430131912231, 0.17561736702919006, 0.03161602467298508, -0.3445986211299896, 0.21483927965164185, 0.08037806302309036, 73.2584228515625, -65.62285614013672, 0.01537322998046875, 8.689796447753906, -0.09672880172729492, -0.0017879828810691833, -1.3815826260810127e-10, -7.884704000815645e-11, 0.02418743260204792, 0.0, 2.3961735373667636e-14, 1.1546319456101628e-14, 0.0, 0.024161411449313164, 0.0, 0.0, 2.2631243125174894e-14, 0.0, 0.00010100983490701765, -4.87890977618477e-19, 1.0880185641326534e-14, 0.0, -4.87890977618477e-19, 0.00010100983490701765]}, {"packed": [0.006798021961003542, -0.03793578967452049, 0.1225954219698906, -0.31169629096984863, 0.07578025758266449, 0.16250228881835938, 0.08012982457876205, 0.027189278975129128, 0.204534649848938, 0.7307887077331543, -0.09756267070770264, -0.03424227237701416, -0.1594821959733963, -0.12964443862438202, -0.05755516141653061, 0.12307727336883545, 0.047276515513658524, 0.1703740507364273, 0.09865853935480118, -0.4804445803165436, -0.0942784994840622, -0.34643715620040894, -0.17713560163974762, -0.031833067536354065, -0.24778738617897034, -0.18998928368091583, -0.24860037863254547, 0.1237298846244812, -0.18905623257160187, 0.1337176412343979, 0.12870550155639648, -0.09091044217348099, -0.1703287661075592, -0.33680668473243713, 0.12243913114070892, 0.07462690025568008, -0.13390792906284332, 0.001983822789043188, 0.023962298408150673, 0.34787675738334656, 0.09957756102085114, 0.011122091673314571, -0.13179457187652588, 0.03352649509906769, 0.5112106204032898, -0.05238516628742218, 0.27153730392456055, -0.11977280676364899, 0.019583677873015404, -0.014571660198271275, 0.3244374990463257, 0.06633639335632324, -0.31169506907463074, 0.039656538516283035, -0.10854078829288483, -0.011637193150818348, -0.29448434710502625, -0.13928459584712982, -0.1003490537405014, 0.15150536596775055, 0.09237141907215118, -0.35496091842651367, 0.13770203292369843, -0.08589478582143784, -0.007329937536269426, -0.08009234815835953, -0.1198546439409256, 0.08538013696670532, -0.22095990180969238, -0.18684208393096924, 0.10407699644565582, 0.20365102589130402, -0.12956830859184265, 0.233455628156662, 0.03405936062335968, 0.2618127763271332, 0.004571372643113136, -0.2506708800792694, 0.0692826360464096, -0.0003193294396623969, 0.16786521673202515, 0.7111766934394836, -0.20423150062561035, 0.1972212940454483, -0.20376703143119812, 0.11903771758079529, 0.02679397165775299, 0.2748829424381256, -0.06091579422354698, -0.03413897380232811, 0.07040131092071533, -0.12202169001102448, 0.05202152207493782, 0.009205542504787445, 0.13989196717739105, 0.09035494178533554, 0.06335750967264175, 0.25158601999282837, -0.31250491738319397, -0.05474291741847992, 0.21769681572914124, 0.1803843080997467, 0.14481288194656372, 0.03285061568021774, 0.12863798439502716, -0.01853884942829609, -0.04544990509748459, 0.12280800193548203, -0.0526534728705883, -0.39805006980895996, 0.5772771835327148, 0.022808825597167015, 0.19229723513126373, -0.1651921272277832, 0.14304478466510773, -0.010724934749305248, -0.25881698727607727, 0.08899768441915512, -0.11559146642684937, 0.5322839021682739, -0.532981812953949, -0.4170287549495697, -0.20547495782375336, 0.2419349104166031, 0.012622891925275326, -0.4568168818950653, 0.16027288138866425, -0.06725841760635376, 182.59735107421875, -162.85842895507812, -0.041071414947509766, 11.013665199279785, -0.13808917999267578, -0.001458495855331421, -1.3815826260810127e-10, -7.884704000815645e-11, 0.024161411449313164, 0.0, 0.0, 0.0, 0.0, 0.024161411449313164, 6.0864399457905e-17, 2.949029909160572e-17, 0.0, 6.085052929339372e-17, 0.00010100983490701765, -4.87890977618477e-19, 0.0, 2.949029909160572e-17, -4.87890977618477e-19, 0.00010100983490701765]}, {"packed": [-0.0011205226182937622, -0.07863352447748184, -0.45209673047065735, -0.1671072542667389, 0.01817065291106701, -0.023053843528032303, -0.09565456956624985, 0.027131114155054092, 0.19688546657562256, 0.7113168239593506, 0.005490054842084646, 0.2913663983345032, -0.038203783333301544, 0.10463273525238037, -0.1173497661948204, 0.45473629236221313, -0.019464481621980667, 0.2840273976325989, 0.13976262509822845, -0.7233635187149048, -0.05788303166627884, -0.4728917181491852, -0.02036711946129799, -0.1358051747083664, -0.11474047601222992, -0.05673426762223244, 0.09647057205438614, 0.06108149513602257, -0.36956968903541565, 0.1258716881275177, 0.10176574438810349, -0.07486406713724136, 0.3309940993785858, 0.12557409703731537, 0.028161535039544106, 0.4622207581996918, -0.07225540280342102, -0.32125869393348694, -0.0035991566255688667, 0.5388669967651367, 0.07717880606651306, -0.0672164037823677, -0.07581356167793274, -0.011617996729910374, 0.6804441809654236, -0.3535497784614563, -0.14152389764785767, -0.08903084695339203, 0.1435907930135727, 0.0777953639626503, -0.47325000166893005, 0.20687077939510345, 0.8756394386291504, 0.008386759087443352, -0.08691152930259705, -0.035809699445962906, 0.11082718521356583, -0.040934182703495026, -0.009802406653761864, 0.3046325147151947, 0.08086530864238739, -0.4998074769973755, 0.05918225273489952, 0.0500061921775341, 0.18502025306224823, -0.20117683708667755, 0.16108135879039764, -0.6564977169036865, -0.22231854498386383, -0.10126087814569473, 0.24672608077526093, 0.25901150703430176, 0.2559490501880646, 0.21494053304195404, 0.04103657975792885, 0.5607531070709229, 0.062236715108156204, -0.10600314289331436, -0.030030136927962303, -0.08983699977397919, 0.008182637393474579, -0.0785207748413086, -0.25136351585388184, 0.5080934166908264, 0.1455277055501938, 0.08528722077608109, 0.04789607971906662, 0.37006402015686035, -0.6090555787086487, 0.017182359471917152, -0.05214308574795723, -0.10482752323150635, 0.08412817120552063, 0.006267251446843147, 0.06043426692485809, 0.04542728140950203, 0.07250446826219559, 0.42357534170150757, 0.036981239914894104, 0.02087152563035488, 0.0719887763261795, 0.5023961067199707, 0.2448241263628006, -0.1283821165561676, 0.01577151007950306, 0.14164692163467407, -0.07471709698438644, 0.2753320038318634, 0.11309092491865158, 0.17161275446414948, 0.24542580544948578, -0.13785865902900696, 0.29492202401161194, 0.579058825969696, 0.012564686127007008, -0.0153117086738348, -0.11800695955753326, 0.054211925715208054, -0.23755879700183868, 0.2766868770122528, -0.44247111678123474, -0.22865022718906403, -0.460102915763855, 0.21972320973873138, 0.009600197896361351, -0.2925001382827759, 0.17873819172382355, 0.1561426967382431, 132.01016235351562, -158.78335571289062, -3.135805368423462, 7.948880672454834, -0.0197145938873291, -0.01723623275756836, -1.3815826260810127e-10, -7.884704000815645e-11, 0.024161411449313164, 0.0, 0.0, 0.0, 0.0, 0.024161411449313164, 0.0, 0.0, 0.0, 0.0, 0.00010100983490701765, -4.87890977618477e-19, 0.0, 0.0, -4.87890977618477e-19, 0.00010100983490701765]}, {"packed": [0.018037598580121994, -0.020103871822357178, 0.024906381964683533, -0.1876850724220276, 0.039508841931819916, -0.0028958143666386604, -0.09148133546113968, 0.023144353181123734, 0.19952392578125, 0.8478073477745056, -0.038192268460989, 0.3354146480560303, -0.07335914671421051, -0.2165079265832901, -0.32142266631126404, 0.36377280950546265, 0.004728034604340792, 0.3253002464771271, 0.14650045335292816, -0.5317760705947876, -0.07178352028131485, -0.5399974584579468, -0.009519826620817184, -0.38451358675956726, -0.21084660291671753, -0.3903529942035675, -0.04567072540521622, 0.06867069005966187, -0.4731391668319702, 0.2722513973712921, 0.17444446682929993, -0.08952422440052032, 0.22582030296325684, -0.21314749121665955, 0.035576652735471725, 0.19193679094314575, -0.10609371215105057, -0.11619840562343597, 0.04789474979043007, 0.6807464361190796, 0.07572095841169357, -0.015650803223252296, -0.07428313791751862, 0.02221432700753212, 0.68128901720047, -0.21157844364643097, 0.14191623032093048, -0.11025086790323257, 0.11470607668161392, 0.023264920338988304, -0.4916244149208069, 0.26027175784111023, -0.19359742105007172, 0.010195094160735607, -0.21616455912590027, -0.028402527794241905, -0.08523485064506531, -0.10303520411252975, -0.026732128113508224, -0.11684253811836243, 0.04350559785962105, -0.4261893332004547, 0.0786832794547081, -0.04213154688477516, 0.23244081437587738, -0.12367594987154007, -0.030071690678596497, 0.07118005305528641, -0.29877352714538574, -0.24040758609771729, 0.21017371118068695, 0.2780575752258301, -0.11259786784648895, 0.18245483934879303, 0.03699088469147682, 0.6050849556922913, 0.02054719626903534, -0.15979625284671783, 0.008404799737036228, -0.06123490259051323, 0.21949949860572815, 0.6873773336410522, -0.24259182810783386, 0.39301416277885437, -0.15332181751728058, 0.15260577201843262, 0.13464300334453583, 0.3210223615169525, 0.07063254714012146, -0.013312723487615585, 0.05969657003879547, -0.10663828253746033, 0.04222247749567032, 0.03899218887090683, 0.03869057446718216, 0.06742828339338303, 0.1042596697807312, 0.41373908519744873, -0.32176607847213745, -0.07678303867578506, 0.18502455949783325, 0.1643436700105667, 0.11398518830537796, -0.08088444173336029, 0.05053221061825752, 0.057532377541065216, -0.053640756756067276, 0.2608270049095154, -0.014193822629749775, -0.4657563865184784, 0.5195179581642151, -0.08163832873106003, 0.26397594809532166, -0.07401233911514282, 0.11709731072187424, 0.04565940797328949, -0.04882694408297539, 0.08089495450258255, -0.12950392067432404, 0.5446219444274902, -0.3195255994796753, -0.39535000920295715, -0.3446289896965027, 0.21955899894237518, 0.04388317093253136, -0.26018330454826355, 0.15245100855827332, 0.016414159908890724, 171.82008361816406, -159.59600830078125, 3.1068832874298096, 8.659163475036621, -0.05538034439086914, -0.004021346569061279, -1.3815826260810127e-10, -7.884704000815645e-11, 0.024161146953701973, 0.0, 2.972145099477963e-14, 1.4432899320127035e-14, 0.0, 0.024161411449313164, 0.0, 0.0, 2.847289393734069e-14, 0.0, 0.00010100983490701765, -4.87890977618477e-19, 1.3822276656583199e-14, 0.0, -4.87890977618477e-19, 0.00010100983490701765]}, {"packed": [0.15130995213985443, -0.006969374138861895, 0.13465359807014465, -0.23667073249816895, -0.06795637309551239, 0.11950033903121948, 0.1762150675058365, 0.011294453404843807, -0.11913811415433884, 0.8812521696090698, -0.09234997630119324, 0.03203212842345238, -0.17490704357624054, -0.2444787621498108, -0.09873950481414795, -0.043001506477594376, 0.03197958320379257, 0.26556146144866943, 0.09396772086620331, -0.411307692527771, -0.10357314348220825, -0.10042400658130646, 0.03389469161629677, -0.1307840198278427, -0.28809741139411926, -0.1088639423251152, -0.2680439054965973, 0.21591757237911224, -0.0032774966675788164, 0.20347057282924652, 0.3450073003768921, -0.1079789251089096, -0.10177098214626312, -0.7243301272392273, 0.3098050653934479, 0.03336179256439209, -0.0637420043349266, 0.010128224268555641, -0.004536105785518885, 0.17922288179397583, 0.05470508709549904, -0.04612205922603607, -0.21913419663906097, 0.12635177373886108, 0.2780444920063019, -0.25393834710121155, 0.334740549325943, -0.10699416697025299, 0.05576728284358978, -0.041101306676864624, 0.5026534199714661, 0.006845977157354355, -0.4786061644554138, 0.0592295341193676, -0.16874746978282928, -0.03592469543218613, -0.32089927792549133, -0.1473371535539627, -0.16037246584892273, 0.15777899324893951, -0.042756088078022, -0.1042114719748497, 0.06762434542179108, -0.2218029797077179, -0.11893312633037567, -0.03706469014286995, -0.14683189988136292, 0.32854968309402466, -0.2663062512874603, -0.1926584243774414, 0.08783327788114548, 0.16499212384223938, -0.11674083769321442, 0.2285197675228119, 0.013913498260080814, 0.1762726604938507, -0.032298676669597626, -0.3187963366508484, 0.100251704454422, 0.011009633541107178, 0.15170586109161377, 0.7822672128677368, -0.3536018133163452, 0.15448324382305145, -0.29175522923469543, 0.23906953632831573, 0.21609757840633392, 0.2034684270620346, -0.033342763781547546, -0.01803199015557766, -0.00525518087670207, -0.03388787433505058, 0.03170248121023178, -0.010118058882653713, -0.017254387959837914, 0.08475415408611298, 0.06697554886341095, 0.2102852612733841, -0.3490355610847473, -0.06104675680398941, 0.18427972495555878, 0.024496285244822502, 0.043510086834430695, 0.02408609353005886, 0.16404767334461212, -0.018186036497354507, -0.025841999799013138, 0.10776031017303467, -0.044263262301683426, -0.417961984872818, 0.710458517074585, 0.11425482481718063, -0.1757214218378067, -0.2640429437160492, 0.14883914589881897, 0.13479943573474884, -0.25286346673965454, 0.1115398034453392, -0.07684680819511414, 0.5851379036903381, -0.6808798313140869, -0.3933120667934418, -0.21600636839866638, 0.173346146941185, 0.013291255570948124, -0.5861517190933228, 0.18829090893268585, -0.09222455322742462, 144.6109161376953, -159.00218200683594, 3.105114221572876, 7.914910316467285, -0.043288230895996094, 0.012594401836395264, -1.3815826260810127e-10, -7.884704000815645e-11, 0.024161146953701973, 0.0, 2.972145099477963e-14, 1.4432899320127035e-14, 0.0, 0.024161411449313164, 0.0, 0.0, 2.847289393734069e-14, 0.0, 0.00010100983490701765, -4.87890977618477e-19, 1.3822276656583199e-14, 0.0, -4.87890977618477e-19, 0.00010100983490701765]}, {"packed": [-0.02114962786436081, -0.09977861493825912, -0.045394472777843475, -0.21872706711292267, 0.034324806183576584, 0.023025043308734894, -0.08499781787395477, 0.046447206288576126, 0.36179420351982117, 0.6546148657798767, 0.04381236433982849, 0.18828842043876648, -0.07652045041322708, 0.09929940849542618, 0.04299288988113403, 0.3697679340839386, 0.03923194855451584, 0.2027776837348938, 0.16369940340518951, -0.7399480938911438, -0.05914528667926788, -0.5443279147148132, -0.06287959218025208, 0.11367323994636536, -0.14643102884292603, -0.1930287629365921, 0.030907897278666496, 0.043668895959854126, -0.31479448080062866, 0.006625561509281397, 0.02299509011209011, -0.07319212704896927, 0.38175123929977417, 0.08097093552350998, 0.02968704327940941, 0.47734335064888, -0.08694088459014893, -0.19618861377239227, 0.025986773893237114, 0.2917764186859131, 0.06617503613233566, 0.02704354003071785, -0.06856155395507812, 0.007279578130692244, 0.6967500448226929, -0.09091275185346603, -0.2936452329158783, -0.06769606471061707, 0.06363467127084732, 0.1984757035970688, -0.4299484193325043, 0.16546311974525452, 0.8523760437965393, 0.00743483891710639, -0.0583982914686203, -0.0041977111250162125, -0.21026122570037842, -0.07067602127790451, -0.006264714058488607, 0.18792228400707245, 0.2015724629163742, -0.5773934721946716, 0.06552465260028839, 0.052896350622177124, 0.11589492857456207, -0.17723354697227478, 0.038447365164756775, -0.579524576663971, -0.2078980803489685, 0.016455523669719696, 0.2445768415927887, 0.2085859626531601, 0.16465811431407928, 0.18774640560150146, 0.05597130209207535, 0.517260730266571, 0.0317038930952549, -0.15730105340480804, -0.01824144460260868, -0.14265292882919312, 0.05624181404709816, -0.03846483305096626, -0.1979674994945526, 0.5532139539718628, 0.1592222899198532, 0.03837282583117485, -0.005912803113460541, 0.39172011613845825, -0.5237380266189575, 0.023779654875397682, -0.01457766443490982, -0.11592765897512436, 0.1354181319475174, -0.039436910301446915, 0.19936636090278625, 0.04731699824333191, 0.05495164543390274, 0.39186081290245056, 9.301337559008971e-05, 0.04856438189744949, 0.11564071476459503, 0.4467217028141022, 0.2157294750213623, -0.10171002149581909, 0.022567415609955788, 0.11100037395954132, -0.070518858730793, 0.3023323714733124, 0.0541364848613739, 0.00414701271802187, 0.3006828725337982, -0.12331891059875488, 0.31993579864501953, 0.5352793335914612, -0.004267830401659012, -0.08942580968141556, -0.21448715031147003, 0.06462941318750381, -0.27283334732055664, 0.2730166018009186, -0.4157131016254425, -0.28433769941329956, -0.27986422181129456, 0.2829533517360687, -0.008744928054511547, -0.3735177516937256, 0.1965017318725586, 0.08539902418851852, 149.8526611328125, -162.27017211914062, -0.009375810623168945, 9.586925506591797, -0.10804271697998047, -0.018937110900878906, -1.3815826260810127e-10, -7.884704000815645e-11, 0.024161146953701973, 0.0, 2.78015457877423e-14, 1.354472090042691e-14, 0.0, 0.024161411449313164, 0.0, 0.0, 2.652567699995209e-14, 0.0, 0.00010100983490701765, -4.87890977618477e-19, 1.2878587085651816e-14, 0.0, -4.87890977618477e-19, 0.00010100983490701765]}, {"packed": [-0.01572427712380886, -0.0454072505235672, -0.1466502547264099, -0.18353064358234406, 0.030195113271474838, 0.040962960571050644, -0.053211841732263565, 0.04753483831882477, 0.14245480298995972, 0.807032585144043, -0.0037160785868763924, 0.20992694795131683, -0.05377710983157158, 0.05417504161596298, -0.166535422205925, 0.2958029508590698, 0.04513721540570259, 0.28488922119140625, 0.1712675541639328, -0.7749223709106445, -0.025911904871463776, -0.5384184718132019, -0.021366924047470093, 0.020772216841578484, -0.11806964874267578, -0.07683880627155304, 0.031128816306591034, 0.04997128248214722, -0.33029934763908386, 0.06289223581552505, 0.013039263896644115, -0.08475309610366821, 0.20373573899269104, 0.046488892287015915, 0.04087243229150772, 0.3979967534542084, -0.09287790209054947, -0.06915033608675003, 0.023001477122306824, 0.23473826050758362, 0.017912153154611588, -0.007300752215087414, -0.08542963117361069, 0.01765718124806881, 0.7042202949523926, -0.20118054747581482, -0.1943255364894867, -0.07226026803255081, 0.06728770583868027, 0.09666991233825684, -0.3543381690979004, 0.15253518521785736, 0.8544201254844666, 0.007621875032782555, -0.08301090449094772, -0.0048375618644058704, -0.08606325089931488, -0.06300664693117142, -0.016908789053559303, 0.39221659302711487, 0.1194329485297203, -0.5868156552314758, 0.061787210404872894, 0.05068890377879143, 0.19110232591629028, -0.17665287852287292, 0.14424245059490204, -0.6329224109649658, -0.20202600955963135, -0.1307334005832672, 0.21519239246845245, 0.20246665179729462, 0.23127345740795135, 0.23187223076820374, 0.050758976489305496, 0.5123481154441833, 0.042408592998981476, -0.13092701137065887, -0.011607905849814415, -0.13350334763526917, 0.031159058213233948, 0.0044385772198438644, -0.26195618510246277, 0.4983404874801636, 0.10310500860214233, 0.07396887987852097, 0.07124600559473038, 0.37633952498435974, -0.5657141804695129, 0.019262881949543953, -0.04050660505890846, -0.10320427268743515, 0.07492558658123016, -0.01195718627423048, 0.1326960325241089, 0.062063176184892654, 0.05511297658085823, 0.42618802189826965, 0.00014162255683913827, 0.03272246569395065, 0.11783571541309357, 0.44965124130249023, 0.20480887591838837, -0.14010746777057648, 0.02461162395775318, 0.09953425079584122, -0.0735800489783287, 0.2415228933095932, 0.10562770813703537, -0.027568167075514793, 0.34881532192230225, -0.09940800070762634, 0.24064917862415314, 0.5598207712173462, 0.01236630603671074, -0.0035192561335861683, -0.14197538793087006, 0.06303492188453674, -0.18816816806793213, 0.30333229899406433, -0.5117461681365967, -0.2765997052192688, -0.38989293575286865, 0.21900330483913422, -0.004369826056063175, -0.45872247219085693, 0.21615777909755707, 0.0990438461303711, 168.85791015625, 49.28824234008789, 0.016958951950073242, 10.521414756774902, -0.1012277603149414, -0.02065563201904297, -1.3815826260810127e-10, -7.884704000815645e-11, 0.024161146953701973, 0.0, 2.78015457877423e-14, 1.354472090042691e-14, 0.0, 0.024161411449313164, 0.0, 0.0, 2.652567699995209e-14, 0.0, 0.00010100983490701765, -4.87890977618477e-19, 1.2878587085651816e-14, 0.0, -4.87890977618477e-19, 0.00010100983490701765]}, {"packed": [-0.014345603995025158, -0.1015038788318634, -0.3477138876914978, -0.16983625292778015, 0.027884164825081825, -0.029412755742669106, -0.11929285526275635, 0.08894379436969757, 0.12172969430685043, 0.5569974780082703, -0.051395658403635025, 0.2579291760921478, -0.021337516605854034, 0.13805091381072998, -0.044361308217048645, 0.3301202952861786, 0.014636926352977753, 0.27900707721710205, 0.18479278683662415, -0.8225727081298828, -0.007241272367537022, -0.45811396837234497, -0.028232820332050323, -0.04148910939693451, -0.06175485625863075, 0.24760539829730988, 0.11784304678440094, 0.060583338141441345, -0.3767186105251312, 0.1558135449886322, 0.040587954223155975, -0.13910548388957977, 0.17495283484458923, 0.15639428794384003, 0.04731748625636101, 0.3798474669456482, -0.11813398450613022, -0.1010485589504242, 0.011295407079160213, 0.29702895879745483, 0.019444076344370842, -0.038407761603593826, -0.0824728012084961, -0.012241700664162636, 0.6924365162849426, -0.26690346002578735, -0.22136534750461578, -0.10885613411664963, 0.08716997504234314, 0.11899194121360779, -0.4488202631473541, 0.21955610811710358, 0.9183350801467896, 0.009818123653531075, -0.07810762524604797, -0.00011700578033924103, 0.18391087651252747, -0.05012603849172592, -0.0007398174493573606, 0.42639386653900146, 0.05238698795437813, -0.5268439054489136, 0.10017281770706177, 0.06866075098514557, 0.2471807897090912, -0.21230727434158325, 0.19175036251544952, -0.7107256054878235, -0.1922314316034317, -0.033364955335855484, 0.1970783919095993, 0.2657654583454132, 0.31354236602783203, 0.2396654486656189, 0.048356249928474426, 0.4561065435409546, 0.0814872458577156, -0.10928156971931458, -0.03727560490369797, -0.13445790112018585, -0.0663004070520401, -0.14363738894462585, -0.2602647840976715, 0.31930238008499146, 0.24630621075630188, 0.07408520579338074, 0.04697135090827942, 0.4007427990436554, -0.6674487590789795, 0.017156455665826797, -0.12908987700939178, -0.0921216830611229, 0.07990413159132004, -0.02154662273824215, -0.05971739441156387, 0.062123097479343414, 0.04542500153183937, 0.456291526556015, 0.1379629373550415, 0.0461890883743763, -0.11554722487926483, 0.5637502670288086, 0.22324948012828827, -0.16427099704742432, 0.013020061887800694, 0.1306694895029068, -0.08097690343856812, 0.2543080747127533, 0.18297691643238068, 0.26910868287086487, 0.2799031138420105, -0.10986435413360596, 0.24293814599514008, 0.5855584144592285, -0.04192196950316429, -0.03977625072002411, -0.06170787289738655, 0.052219610661268234, -0.2348000407218933, 0.08991723507642746, -0.49337926506996155, -0.22617995738983154, -0.4997742474079132, 0.2003333866596222, -0.0021569852251559496, -0.3287455439567566, 0.34607821702957153, 0.16912943124771118, 131.64073181152344, 52.085880279541016, -3.129995584487915, 7.693161964416504, -0.10030651092529297, -0.022204160690307617, -1.3815826260810127e-10, -7.884704000815645e-11, 0.024161146953701973, 2.6726176827196468e-11, 2.78015457877423e-14, 1.354472090042691e-14, 1.468078991706534e-10, 0.02415470965206623, 3.069528138610611e-14, 1.4904744105592727e-14, 2.652567699995209e-14, -9.736084686942995e-16, 0.00010100983490701765, -4.87890977618477e-19, 1.2878587085651816e-14, -4.718447854656915e-16, -4.87890977618477e-19, 0.00010100983490701765]}, {"packed": [0.0034941015765070915, -0.029727766290307045, -0.12806735932826996, -0.2269473522901535, 0.03485795482993126, 0.0006222829106263816, -0.1985512226819992, -0.08803233504295349, 0.14299994707107544, 0.7919982671737671, -0.18394039571285248, 0.34192392230033875, -0.07009079307317734, -0.08870518207550049, -0.289632111787796, 0.40699008107185364, -0.009379840455949306, 0.33167538046836853, 0.1636771559715271, -0.755050539970398, -0.04839871823787689, -0.5227576494216919, -0.02200303040444851, -0.3665448725223541, -0.2031051516532898, -0.04444869980216026, 0.03602471947669983, 0.07891181111335754, -0.39345550537109375, 0.2658802568912506, 0.1659194380044937, -0.10041385143995285, 0.030133061110973358, -0.03509046509861946, 0.031125342473387718, 0.4113754332065582, -0.09773141890764236, -0.15606924891471863, -0.00495753763243556, 0.6006744503974915, 0.050596870481967926, -0.03631679341197014, -0.0688919797539711, -0.0021368940360844135, 0.732731819152832, -0.1401223987340927, 0.13958922028541565, -0.14736665785312653, 0.1363804191350937, 0.05044976994395256, -0.40033817291259766, 0.34128761291503906, 0.5770257115364075, 0.008671650663018227, -0.11980811506509781, -0.008500269614160061, 0.1926267445087433, -0.049592889845371246, -0.010520176962018013, 0.10880577564239502, -0.011414709500968456, -0.5106537342071533, 0.08762745559215546, 0.039306025952100754, 0.3037574291229248, -0.1887497752904892, 0.17780818045139313, -0.5599370002746582, -0.26849693059921265, -0.17331314086914062, 0.2090231478214264, 0.30466946959495544, 0.23010623455047607, 0.2564454674720764, 0.035327084362506866, 0.5584167838096619, 0.04607156291604042, -0.10598750412464142, -0.01578962802886963, -0.10251357406377792, 0.04150767624378204, 0.2658030390739441, -0.2545830011367798, 0.34899815917015076, 0.006393840070813894, 0.12595243752002716, 0.10479075461626053, 0.36347073316574097, -0.49829789996147156, 0.007027539890259504, -0.0005747645627707243, -0.09525246173143387, 0.035707492381334305, 0.027327531948685646, -0.08189039677381516, 0.060656122863292694, 0.06135575845837593, 0.4978290796279907, -0.06725188344717026, -0.03243565931916237, 0.131943479180336, 0.46706339716911316, 0.200728178024292, -0.1285470575094223, 0.01959856040775776, 0.07937907427549362, -0.06617163121700287, 0.22674676775932312, 0.09789109975099564, -0.04732690006494522, 0.3715059757232666, -0.12218957394361496, 0.23326915502548218, 0.5033872723579407, 0.04858194291591644, 0.04118119925260544, -0.06941752135753632, 0.06591112166643143, -0.16780172288417816, 0.3602854013442993, -0.3351917266845703, -0.28006890416145325, -0.5004615187644958, 0.15271632373332977, 0.028006218373775482, -0.34009429812431335, 0.21150001883506775, 0.14022694528102875, 151.98658752441406, 0.6453437805175781, 1.5516893863677979, 9.954705238342285, -0.05963945388793945, -0.011045217514038086, -1.3815826260810127e-10, -7.884704000815645e-11, 0.024161146953701973, 1.4263035197359386e-11, 2.972145099477963e-14, 1.4432899320127035e-14, 1.36519684446057e-11, 0.024161411449313164, -4.8691519566324e-16, -2.3592239273284576e-16, 2.847289393734069e-14, -4.868042343471497e-16, 0.00010100983490701765, -4.87890977618477e-19, 1.3822276656583199e-14, -2.3592239273284576e-16, -4.87890977618477e-19, 0.00010100983490701765]}, {"packed": [-0.021989313885569572, -0.00046134612057358027, -0.36481544375419617, -0.17347095906734467, 0.04733806848526001, 0.07577349990606308, -0.06412530690431595, 0.013396267779171467, 0.2870074212551117, 0.8511801362037659, -0.05813772231340408, 0.22449301183223724, -0.060376618057489395, -0.20725035667419434, -0.29640108346939087, 0.4392957091331482, 0.036972466856241226, 0.2945111095905304, 0.14137233793735504, -0.5909274220466614, -0.04274363815784454, -0.5747880935668945, -0.035669613629579544, -0.08573012053966522, -0.05164521932601929, -0.08610272407531738, 0.05624799057841301, 0.07940230518579483, -0.5189403891563416, 0.23550324141979218, 0.07909650355577469, -0.08736539632081985, 0.2263796478509903, -0.07250718772411346, 0.037701837718486786, 0.1618386209011078, -0.11122343689203262, -0.07336457073688507, 0.05002026632428169, 0.6000221967697144, 0.07775474339723587, -0.04432190954685211, -0.09448552131652832, 0.03353689983487129, 0.7511263489723206, -0.1702011227607727, 0.14963486790657043, -0.09698336571455002, 0.07778050750494003, 0.059589602053165436, -0.28114333748817444, 0.29022568464279175, 0.4807385504245758, 0.014423074200749397, -0.19139575958251953, -0.014183307066559792, 0.06043415516614914, -0.08231750875711441, -0.035807810723781586, 0.21530696749687195, 0.011291529051959515, -0.6634594202041626, 0.08012491464614868, -0.029359925538301468, 0.2012646496295929, -0.15649935603141785, 0.1357116997241974, -0.4957912564277649, -0.19943727552890778, -0.23354457318782806, 0.18924108147621155, 0.2672572433948517, 0.11181345582008362, 0.29426348209381104, 0.06726229190826416, 0.6297630667686462, 0.05766480788588524, -0.14714567363262177, 0.007359533570706844, -0.12093693763017654, 0.08099158853292465, 0.47195494174957275, -0.21272100508213043, 0.3684617578983307, 0.05183941498398781, 0.14563150703907013, 0.08886384218931198, 0.4238780736923218, -0.45821842551231384, -0.0092757698148489, 0.012725243344902992, -0.07314122468233109, 0.03960542753338814, 0.03384176641702652, -0.195947527885437, 0.0644085481762886, 0.0958099216222763, 0.4633174538612366, -0.147660031914711, -0.06000332906842232, 0.1477476954460144, 0.3932689130306244, 0.18570594489574432, -0.15670254826545715, 0.028153875842690468, 0.094103142619133, -0.0637393668293953, 0.2115917205810547, 0.07967130094766617, -0.23238585889339447, 0.37912243604660034, -0.10463788360357285, 0.3430712819099426, 0.3977817893028259, 0.0524677149951458, -0.006972595117986202, 0.06643817573785782, 0.046384140849113464, -0.11004512757062912, 0.4410502016544342, -0.4015430808067322, -0.36024385690689087, -0.4865477979183197, 0.2292562872171402, 0.01580476015806198, -0.2779778242111206, 0.1743939071893692, 0.06376657634973526, 152.0218963623047, 25.22399139404297, 1.5400502681732178, 8.731935501098633, -0.09899330139160156, -0.009769260883331299, -1.3815826260810127e-10, -7.884704000815645e-11, 0.024161146953701973, 1.3363088413598234e-11, 2.78015457877423e-14, 1.354472090042691e-14, 1.2752021660844548e-11, 0.024161411449313164, -4.8691519566324e-16, -2.3592239273284576e-16, 2.652567699995209e-14, -4.868042343471497e-16, 0.00010100983490701765, -4.87890977618477e-19, 1.2878587085651816e-14, -2.3592239273284576e-16, -4.87890977618477e-19, 0.00010100983490701765]}, {"packed": [-0.023791927844285965, -0.08543599396944046, -0.2817845940589905, -0.1578926295042038, 0.02516993321478367, 0.0270229484885931, -0.06031594052910805, 0.02671671472489834, 0.0999821200966835, 0.6036940217018127, 0.009334566071629524, 0.18646866083145142, -0.028957951813936234, 0.10476044565439224, -0.10742158442735672, 0.2265346646308899, 0.04577784612774849, 0.2781573235988617, 0.1648714691400528, -0.799358069896698, -0.02701009064912796, -0.3870970904827118, -0.030382627621293068, 0.10378537327051163, 0.005739604588598013, 0.111464723944664, 0.057753805071115494, 0.05251351743936539, -0.2932530641555786, 0.07134857028722763, -0.009612605907022953, -0.11765336990356445, 0.08948558568954468, 0.13291792571544647, 0.0703636184334755, 0.29937803745269775, -0.12451744079589844, 0.0120807234197855, 0.031155245378613472, 0.06343405693769455, -0.006498393602669239, -0.021915387362241745, -0.10086959600448608, -0.00010178067168453708, 0.5878746509552002, -0.32475951313972473, -0.28926292061805725, -0.08142643421888351, 0.06592273712158203, 0.09811652451753616, -0.28449830412864685, 0.11007682979106903, 0.9234060049057007, 0.011578232049942017, -0.07006208598613739, 0.0028209954034537077, 0.007584193255752325, -0.06557530909776688, -0.013907956890761852, 0.4933112859725952, 0.1165919378399849, -0.4763184189796448, 0.07063078880310059, 0.08455320447683334, 0.21816062927246094, -0.19034641981124878, 0.18086297810077667, -0.6990195512771606, -0.1648581326007843, -0.1268896907567978, 0.1753331422805786, 0.20080024003982544, 0.29691940546035767, 0.20510192215442657, 0.04855293035507202, 0.3891657590866089, 0.0657198503613472, -0.12751947343349457, -0.027460439130663872, -0.11579469591379166, -0.0738440752029419, -0.17109708487987518, -0.2628949284553528, 0.34427547454833984, 0.2180844247341156, 0.07146521657705307, 0.027547411620616913, 0.35806843638420105, -0.6472638845443726, 0.027762874960899353, -0.11676944047212601, -0.11182025074958801, 0.09280093014240265, -0.038610465824604034, 0.009692355059087276, 0.06557530164718628, 0.047711655497550964, 0.39540576934814453, 0.1452300101518631, 0.07078517973423004, -0.051132164895534515, 0.5032846331596375, 0.22996053099632263, -0.16367468237876892, 0.024165676906704903, 0.12313809245824814, -0.09214941412210464, 0.21393190324306488, 0.19260931015014648, 0.17761443555355072, 0.30076855421066284, -0.0889153778553009, 0.21960291266441345, 0.6014273762702942, -0.030785145238041878, -0.022691233083605766, -0.14626452326774597, 0.06209816411137581, -0.2016804963350296, 0.10948610305786133, -0.5731912851333618, -0.22676774859428406, -0.4141062796115875, 0.225484237074852, -0.00980832614004612, -0.489923894405365, 0.30180633068084717, 0.10616813600063324, 128.40989685058594, 49.48931121826172, 0.021623611450195312, 7.460013389587402, -0.11484098434448242, -0.02140629291534424, -1.3815826260810127e-10, -7.884704000815645e-11, 0.024161146953701973, -2.7919710987589497e-10, -2.3961735373667636e-14, -1.1546319456101628e-14, -2.865299109089392e-10, 0.024161146953701973, 2.972145099477963e-14, 1.4432899320127035e-14, -2.2631243125174894e-14, 2.847289393734069e-14, 0.00010100983490701765, -4.87890977618477e-19, -1.1102230246251565e-14, 1.3822276656583199e-14, -4.87890977618477e-19, 0.00010100983490701765]}, {"packed": [-0.007953177206218243, -0.037407178431749344, -0.562008798122406, -0.18530264496803284, 0.017287226393818855, -0.010560383088886738, -0.10322785377502441, -0.14073295891284943, 0.34538835287094116, 0.7537475228309631, -0.042881984263658524, 0.24198633432388306, -0.07268697768449783, -0.08049724251031876, -0.19766955077648163, 0.5871090888977051, -0.027052991092205048, 0.24040833115577698, 0.10011422634124756, -0.642716646194458, -0.09568344056606293, -0.37696895003318787, -0.032784488052129745, -0.11541508883237839, -0.06439852714538574, -0.26304298639297485, 0.05484908074140549, 0.06361021846532822, -0.38285261392593384, 0.17704102396965027, 0.043496403843164444, -0.04935947060585022, 0.3364684283733368, 0.07837999612092972, 0.02296041138470173, 0.3007003664970398, -0.0762956514954567, -0.3577192425727844, 0.011200614273548126, 0.7272126078605652, 0.07836039364337921, -0.08455967158079147, -0.05733409523963928, -0.004844208713620901, 0.6728821396827698, -0.1641847789287567, -0.05999140441417694, -0.07658099383115768, 0.11136262118816376, 0.04351252317428589, -0.33778154850006104, 0.20556551218032837, 0.7980459332466125, 0.011166457086801529, -0.09910012036561966, -0.029259417206048965, 0.10078515112400055, -0.047853272408246994, -0.015322004444897175, 0.2086499035358429, 0.13281244039535522, -0.5261252522468567, 0.04817638918757439, 0.012443914078176022, 0.12118849903345108, -0.18754810094833374, 0.15430523455142975, -0.6295429468154907, -0.2026536762714386, -0.18132604658603668, 0.27172422409057617, 0.2853740155696869, 0.07883162796497345, 0.23734787106513977, 0.06693101674318314, 0.6500767469406128, 0.05190972983837128, -0.12302680313587189, -0.016774943098425865, -0.06488332897424698, 0.03626187518239021, 0.22795714437961578, -0.20382194221019745, 0.49558547139167786, 0.14431576430797577, 0.15099604427814484, 0.009757984429597855, 0.4001716375350952, -0.5763602256774902, 0.00955543015152216, 0.010195303708314896, -0.0974680706858635, 0.0818132683634758, 0.02342154271900654, -0.05635036900639534, 0.03819549083709717, 0.10400617122650146, 0.40569570660591125, -0.07910105586051941, -0.03507527336478233, 0.15428689122200012, 0.40294134616851807, 0.2951033115386963, -0.1349148154258728, 0.02365608885884285, 0.16469046473503113, -0.07360018789768219, 0.2523101270198822, 0.09060753881931305, -0.02054251730442047, 0.21334438025951385, -0.14720530807971954, 0.3679756820201874, 0.4948575794696808, 0.04870307072997093, -0.009017543867230415, -0.10790597647428513, 0.04774835705757141, -0.1842007339000702, 0.3639107942581177, -0.380874902009964, -0.292162150144577, -0.42798247933387756, 0.2810989022254944, 0.018139412626624107, -0.2881343364715576, 0.10874579846858978, 0.09911075979471207, 0.89227294921875, -159.85081481933594, -1.574341893196106, 11.671928405761719, -0.031183242797851562, -0.014027833938598633, -1.3815826260810127e-10, -7.884704000815645e-11, 0.024161146953701973, 2.8526070394718772e-11, 2.972145099477963e-14, 1.4432899320127035e-14, 8.795586481369355e-11, 0.02415470965206623, 3.069528138610611e-14, 1.4904744105592727e-14, 2.847289393734069e-14, -9.736084686942995e-16, 0.00010100983490701765, -4.87890977618477e-19, 1.3822276656583199e-14, -4.718447854656915e-16, -4.87890977618477e-19, 0.00010100983490701765]}, {"packed": [0.0465417243540287, -0.003671651938930154, 0.20563176274299622, -0.12694527208805084, -0.03204527497291565, 0.13931791484355927, 0.03582557663321495, -0.027538254857063293, 0.16868527233600616, 0.7654958367347717, 0.09437106549739838, -0.0630682110786438, -0.19931650161743164, -0.09197428822517395, -0.08214888721704483, -0.10196825116872787, 0.09034433960914612, 0.1746135652065277, 0.1158214658498764, -0.12236049771308899, -0.15715277194976807, -0.3928065896034241, -0.09058164805173874, -0.044859301298856735, -0.25604361295700073, -0.6526755690574646, -0.29179850220680237, 0.08413775265216827, -0.10342928767204285, 0.07812559604644775, 0.13949370384216309, -0.05729927122592926, 0.0003661781083792448, -0.6625432372093201, 0.14833487570285797, 0.052513934671878815, -0.11703327298164368, -0.012823213823139668, 0.012901991605758667, 0.27607184648513794, 0.04093172401189804, 0.09234161674976349, -0.08604912459850311, 0.05324519798159599, 0.09343226253986359, -0.02867959812283516, 0.45121192932128906, -0.10646594315767288, 0.011455025523900986, -0.028715992346405983, 0.07733207941055298, -0.04933350905776024, -0.4525899887084961, 0.023103170096874237, -0.16887500882148743, -0.004496488720178604, -0.6054656505584717, -0.2806107997894287, -0.17738409340381622, -0.13301588594913483, 0.17703284323215485, -0.12160930782556534, 0.055970851331949234, -0.2191774696111679, -0.2053917497396469, -0.05449922755360603, -0.24500185251235962, 0.5375620722770691, -0.29491814970970154, -0.11580035090446472, -0.015374747104942799, 0.0988662838935852, -0.3001983165740967, 0.21340082585811615, 0.029297560453414917, 0.2683751583099365, -0.0756472647190094, -0.3539886474609375, 0.08025351911783218, 0.03583601117134094, 0.2958008348941803, 0.7890589237213135, -0.1531064361333847, 0.2988673448562622, -0.19684216380119324, 0.05785477161407471, 0.08615800738334656, 0.05682247877120972, 0.19242942333221436, -0.040632233023643494, 0.06776705384254456, -0.055834926664829254, 0.06851658970117569, -0.035408709198236465, 0.2584061026573181, 0.08249245584011078, 0.09818276017904282, 0.1657513827085495, -0.47030043601989746, -0.05371168628334999, 0.25144410133361816, 0.08594765514135361, 0.005688892211765051, 0.01304799783974886, 0.21940667927265167, -0.11646868288516998, -0.0036095345858484507, -0.0043585277162492275, -0.07232000678777695, -0.5097212791442871, 0.578763484954834, -0.021438853815197945, 0.0527801439166069, -0.4593718349933624, 0.2190033495426178, -0.02182546630501747, -0.4275546669960022, 0.11054077744483948, -0.09175647050142288, 0.5072605013847351, -0.4810696542263031, -0.5047153234481812, 0.03143204748630524, 0.29797762632369995, 0.023279301822185516, -0.49877050518989563, 0.07986831665039062, -0.09866199642419815, -49.98374557495117, -150.06153869628906, 2.038980722427368, 7.794874668121338, -0.13624858856201172, 0.02218484878540039, -1.3815826260810127e-10, -7.884704000815645e-11, 0.024161411449313164, 0.0, 0.0, 0.0, 0.0, 0.02415470965206623, -3.069528138610611e-14, -1.4932499681208355e-14, 0.0, 9.736084686942995e-16, 0.00010100983490701765, -4.87890977618477e-19, 0.0, 4.718447854656915e-16, -4.87890977618477e-19, 0.00010100983490701765]}, {"packed": [0.07753659784793854, 0.026015471667051315, 0.2325923591852188, -0.24633771181106567, 0.18678803741931915, 0.08594250679016113, 0.046189431101083755, -0.15897029638290405, 0.009870355948805809, 0.879925012588501, -0.18399205803871155, 0.27795708179473877, -0.13669733703136444, -0.3480127155780792, -0.2945268154144287, 0.215570867061615, 0.010140495374798775, 0.3589613437652588, 0.12626715004444122, -0.5020744204521179, -0.08138983696699142, -0.3677927851676941, 0.006725846324115992, -0.19802223145961761, -0.2216668576002121, -0.1961076408624649, -0.2966921925544739, 0.195622056722641, -0.1913432627916336, 0.3374437987804413, 0.43608319759368896, -0.09138630330562592, -0.2963320016860962, -0.6310573220252991, 0.11421433836221695, 0.07150612771511078, -0.09749691188335419, 0.012515667825937271, 0.008082942105829716, 0.5817961096763611, 0.041178930550813675, -0.049858227372169495, -0.14527302980422974, 0.04093579947948456, 0.5996829867362976, -0.13036830723285675, 0.49085113406181335, -0.19858995079994202, 0.08363686501979828, -0.040775831788778305, 0.19913934171199799, 0.30728310346603394, -0.6046976447105408, 0.035031285136938095, -0.25325867533683777, -0.024206867441534996, -0.10856323689222336, -0.11351412534713745, -0.10002848505973816, 0.01776331290602684, -0.10030284523963928, -0.28736546635627747, 0.07498656958341599, -0.13716451823711395, 0.2299131155014038, -0.02681831084191799, 0.006095286458730698, 0.24932223558425903, -0.2633334994316101, -0.21919116377830505, 0.1340455412864685, 0.2758476734161377, -0.12261028587818146, 0.1983414888381958, 0.017838917672634125, 0.37543633580207825, 0.023417338728904724, -0.2070414125919342, 0.05116286873817444, -0.050152383744716644, 0.23624517023563385, 0.8558919429779053, -0.25855880975723267, 0.14012055099010468, -0.25139904022216797, 0.29850345849990845, 0.19470171630382538, 0.2698802649974823, 0.07516692578792572, -0.03163962811231613, 0.03897533193230629, -0.03100464679300785, 0.016199782490730286, 0.05392681807279587, -0.31828123331069946, 0.08910716325044632, 0.06740390509366989, 0.32497331500053406, -0.42431360483169556, -0.06571701169013977, 0.10392312705516815, 0.017636604607105255, 0.08453661948442459, -0.027880743145942688, 0.08323940634727478, 0.018306033685803413, -0.03802070766687393, 0.13915428519248962, 0.02196125127375126, -0.4396086633205414, 0.6536313891410828, -0.013748928904533386, 0.008850987069308758, -0.26749661564826965, 0.20520973205566406, 0.15458573400974274, -0.004336565267294645, 0.10105197131633759, -0.06239479035139084, 0.6182166934013367, -0.4350825250148773, -0.39760062098503113, -0.24864941835403442, 0.15638388693332672, 0.04778915271162987, -0.44868600368499756, 0.18014878034591675, -0.05296826362609863, -38.39055633544922, -209.34210205078125, 1.6831753253936768, 9.177638053894043, -0.042464256286621094, 0.008569061756134033, -1.3815826260810127e-10, -7.884704000815645e-11, 0.024161146953701973, 0.0, 2.972145099477963e-14, 1.4432899320127035e-14, 0.0, 0.024161411449313164, 0.0, 0.0, 2.847289393734069e-14, 0.0, 0.00010100983490701765, -4.87890977618477e-19, 1.3822276656583199e-14, 0.0, -4.87890977618477e-19, 0.00010100983490701765]}, {"packed": [0.01497185043990612, 0.016669269651174545, -0.2627529799938202, -0.13189704716205597, 0.04656027629971504, 0.06721087545156479, -0.04220050573348999, -0.037617266178131104, 0.02074475586414337, 0.9258618354797363, -0.06034215912222862, 0.34733515977859497, -0.05272943526506424, -0.3547159433364868, -0.4236108362674713, 0.35145729780197144, 0.02310323528945446, 0.47641339898109436, 0.10166041553020477, -0.6005143523216248, -0.039303530007600784, -0.5704500079154968, 0.013265932910144329, -0.19573640823364258, -0.06274275481700897, 0.01963471621274948, 0.01566545106470585, 0.10627920180559158, -0.5268393754959106, 0.3354146480560303, 0.23309051990509033, -0.09227263182401657, 0.07205525785684586, -0.4122544825077057, 0.03822951763868332, 0.15018624067306519, -0.06343381851911545, -0.07900752872228622, 0.02941444143652916, 0.6639216542243958, 0.04439298063516617, -0.07089941203594208, -0.12861742079257965, 0.05557854846119881, 0.7642866373062134, -0.3788360357284546, 0.3038704991340637, -0.10282403975725174, 0.13916444778442383, -0.011487704701721668, -0.2979224622249603, 0.32755807042121887, -0.10188229382038116, 0.012873266823589802, -0.27042943239212036, -0.048948734998703, 0.12938430905342102, -0.06356342136859894, -0.03954070806503296, 0.143321692943573, -0.11481525748968124, -0.5796388387680054, 0.06669485569000244, -0.07308917492628098, 0.37481576204299927, -0.0979979857802391, 0.21282564103603363, -0.22346022725105286, -0.23301348090171814, -0.3188064694404602, 0.13720300793647766, 0.2882159352302551, 0.13604015111923218, 0.23457889258861542, 0.027983663603663445, 0.6084021925926208, 0.0670861080288887, -0.12008456140756607, 0.022430822253227234, -0.08711597323417664, 0.1504492610692978, 0.6864219307899475, -0.27403974533081055, 0.2769100069999695, -0.13156361877918243, 0.19317063689231873, 0.1826259195804596, 0.3496566712856293, -0.1961684674024582, -0.010237419977784157, 0.019476471468806267, -0.06176791340112686, 0.016893954947590828, 0.06204114109277725, -0.25234535336494446, 0.06608190387487411, 0.10274861007928848, 0.4708101749420166, -0.27220889925956726, -0.06879542022943497, 0.14046801626682281, 0.30335715413093567, 0.10491737723350525, -0.1273876428604126, 0.033507708460092545, 0.07335701584815979, -0.05937163904309273, 0.18141846358776093, 0.06545193493366241, -0.35424378514289856, 0.513343095779419, -0.10210523009300232, 0.21404504776000977, 0.16867166757583618, 0.10021668672561646, 0.08020757883787155, 0.19612237811088562, 0.052895549684762955, -0.04944195970892906, 0.5318959951400757, -0.3764961361885071, -0.35770633816719055, -0.5432686805725098, 0.1563863605260849, 0.035418007522821426, -0.28319668769836426, 0.19519296288490295, 0.062455616891384125, -40.876285552978516, -192.3191375732422, 1.6345317363739014, 8.868340492248535, -0.007568001747131348, -0.0060013532638549805, -1.3815826260810127e-10, -7.884704000815645e-11, 0.024161411449313164, 1.1160516955044386e-13, -4.8691519566324e-16, -2.3592239273284576e-16, 1.1160516955044386e-13, 0.024161411449313164, 2.399881508796664e-16, 1.1796119636642288e-16, -4.868042343471497e-16, 2.3993267022162125e-16, 0.00010100983490701765, -4.87890977618477e-19, -2.3592239273284576e-16, 1.1796119636642288e-16, -4.87890977618477e-19, 0.00010100983490701765]}, {"packed": [0.00026899235672317445, 0.03589329496026039, 0.04434290900826454, -0.22599641978740692, 0.06709664314985275, 0.004350059665739536, -0.181989848613739, -0.0532340370118618, 0.27199313044548035, 0.682101309299469, -0.13757194578647614, 0.22965611517429352, -0.11332075297832489, -0.209042027592659, -0.22344987094402313, 0.37936830520629883, -0.0014367196708917618, 0.22624661028385162, 0.13397017121315002, -0.5859361886978149, -0.07151995599269867, -0.3862636387348175, -0.062106553465127945, -0.19686786830425262, -0.028868993744254112, -0.07548012584447861, -0.18949559330940247, 0.10810177773237228, -0.39546290040016174, 0.30581235885620117, 0.18057946860790253, -0.12225852906703949, -0.292045533657074, -0.059290990233421326, 0.06707179546356201, 0.12292316555976868, -0.14531874656677246, 0.002094385214149952, 0.01676304079592228, 0.5528947710990906, 0.08436450362205505, 0.0003547937667462975, -0.07827825099229813, 0.009836114943027496, 0.6546084880828857, 0.0012055971892550588, 0.23419544100761414, -0.12336795032024384, 0.05241251736879349, 0.041614074259996414, -0.29407817125320435, 0.38117846846580505, -0.06184002012014389, 0.01751425489783287, -0.20326702296733856, -0.0022807077039033175, 0.03652862831950188, -0.1247907429933548, -0.042226046323776245, -0.06872186064720154, 0.06138132885098457, -0.41607657074928284, 0.13494083285331726, -0.0129834720864892, 0.24352984130382538, -0.14584359526634216, 0.007948840968310833, -0.31677988171577454, -0.23342616856098175, -0.2977747619152069, 0.16547061502933502, 0.34700149297714233, -0.08151267468929291, 0.2527734041213989, 0.03494302183389664, 0.49724283814430237, 0.04368748515844345, -0.16289733350276947, 0.02678428404033184, -0.0622711256146431, 0.08764383941888809, 0.6158257722854614, -0.16648687422275543, 0.11073460429906845, -0.045783087611198425, 0.1843959093093872, 0.032571908086538315, 0.34726589918136597, -0.3034071624279022, -0.02651076391339302, 0.0838397815823555, -0.09542348980903625, 0.040645696222782135, 0.03521692380309105, -0.1621280014514923, 0.07118314504623413, 0.08035746961832047, 0.4337795674800873, -0.21964679658412933, -0.06761563569307327, 0.1581038534641266, 0.15286394953727722, 0.18376335501670837, -0.09658965468406677, 0.0410955548286438, 0.06073815003037453, -0.06398932635784149, 0.19559825956821442, 0.060234103351831436, -0.40248915553092957, 0.4593973755836487, -0.05696956813335419, 0.2587670683860779, 0.09135135263204575, 0.09462147951126099, 0.006205559708178043, -0.036958787590265274, 0.06470837444067001, -0.15055514872074127, 0.4226115942001343, -0.3261486291885376, -0.43323400616645813, -0.45960327982902527, 0.24631626904010773, 0.033783212304115295, -0.3151540756225586, 0.2056528478860855, -0.009155572392046452, 0.9568328857421875, -132.68637084960938, -1.5804747343063354, 9.769891738891602, -0.12166547775268555, 0.00037575699388980865, -1.3815826260810127e-10, -7.884704000815645e-11, 0.024161411449313164, 0.0, 0.0, 0.0, 0.0, 0.024161411449313164, 1.0477797557535695e-16, 4.85722573273506e-17, 0.0, 1.0475732914726763e-16, 0.00010100983490701765, -4.87890977618477e-19, 0.0, 4.85722573273506e-17, -4.87890977618477e-19, 0.00010100983490701765]}, {"packed": [-0.009457400999963284, -0.12072472274303436, 0.10849985480308533, -0.24587935209274292, 0.0458056665956974, 0.017848415300250053, -0.1149468645453453, -0.06611737608909607, 0.15257836878299713, 0.3047299385070801, -0.030575403943657875, 0.12422908842563629, -0.07896025478839874, 0.003746409434825182, 0.015547297894954681, 0.11576191335916519, 0.02626933716237545, 0.2261589616537094, 0.13549496233463287, -0.7776376605033875, -0.07045842707157135, -0.24447990953922272, -0.0761072114109993, 0.09160664677619934, 0.03649740666151047, 0.05001477897167206, -0.09643780440092087, 0.07555991411209106, -0.22121934592723846, 0.22518862783908844, -0.00244859023950994, -0.19069302082061768, -0.18104712665081024, 0.08951402455568314, 0.1295773684978485, 0.1816796511411667, -0.20192232728004456, 0.11226240545511246, 0.013552389107644558, 0.059613391757011414, -0.002917834324762225, 0.03644212335348129, -0.057857777923345566, -0.0015511437086388469, 0.4374956488609314, -0.07766404747962952, -0.21893584728240967, -0.10113898664712906, 0.0022934619337320328, 0.1109139695763588, -0.30358996987342834, 0.13952656090259552, 0.8577022552490234, 0.014272892847657204, -0.07534052431583405, 0.01075050886720419, 0.05646185949444771, -0.10928952693939209, 0.013068467378616333, 0.3093298077583313, 0.14959874749183655, -0.2598923146724701, 0.12576426565647125, 0.16036270558834076, 0.18809229135513306, -0.19441114366054535, 0.07820949703454971, -0.6240342259407043, -0.1816236674785614, -0.07376869767904282, 0.14463578164577484, 0.210487961769104, 0.2530214488506317, 0.2147163301706314, 0.044809434562921524, 0.2415883094072342, 0.0554802268743515, -0.14208468794822693, -0.04412584751844406, -0.06519567221403122, -0.1766694188117981, -0.16047614812850952, -0.18968310952186584, 0.10517063736915588, 0.24507330358028412, 0.05785379186272621, -0.05432922765612602, 0.3153310716152191, -0.5593010783195496, 0.05924595147371292, -0.028485244140028954, -0.14699119329452515, 0.10581760853528976, -0.0627274438738823, -0.029606228694319725, 0.046335142105817795, 0.032060153782367706, 0.3250040113925934, 0.21271048486232758, 0.10012661665678024, -0.08245885372161865, 0.49885523319244385, 0.25969430804252625, -0.1622561812400818, 0.030033882707357407, 0.08614302426576614, -0.09995079785585403, 0.17233753204345703, 0.21840900182724, 0.1694490611553192, 0.30560988187789917, -0.10690261423587799, 0.20092454552650452, 0.5647714138031006, -0.12130812555551529, -0.07616113126277924, -0.2315690517425537, 0.08030933886766434, -0.2123377025127411, -0.10314812511205673, -0.5299990773200989, -0.20734696090221405, -0.360750675201416, 0.24159088730812073, -0.0013467030366882682, -0.5459377765655518, 0.29640644788742065, 0.05668629705905914, -25.033815383911133, -4.130252838134766, -0.00863337516784668, 9.505261421203613, -0.17313194274902344, -0.006063878536224365, -1.3815826260810127e-10, -7.884704000815645e-11, 0.024161411449313164, 0.0, 0.0, 0.0, 0.0, 0.024161411449313164, 0.0, 0.0, 0.0, 0.0, 0.00010100983490701765, -4.87890977618477e-19, 0.0, 0.0, -4.87890977618477e-19, 0.00010100983490701765]}, {"packed": [0.01968718320131302, -0.12450402975082397, 0.010292698629200459, -0.2730623185634613, -0.27417466044425964, 0.15686848759651184, 0.12251506000757217, 0.22086496651172638, 0.02221646159887314, 0.6890307664871216, -0.16985256969928741, 0.03902937099337578, -0.09673459082841873, 0.1397455483675003, 0.26871833205223083, -0.04213523864746094, 0.03697294741868973, 0.1422511637210846, 0.10115658491849899, -0.7032793164253235, 0.042056743055582047, -0.03751251846551895, -0.23470357060432434, 0.06115705519914627, -0.19226332008838654, 0.29233404994010925, -0.14970728754997253, 0.2183043658733368, -0.09164981544017792, 0.08385168015956879, 0.0849936306476593, -0.1824146956205368, -0.29262661933898926, 0.10712559521198273, 0.29233410954475403, 0.09744032472372055, -0.07208108901977539, -0.02103390358388424, 0.0010843039490282536, -0.06342148780822754, 0.16675318777561188, -0.07309471070766449, -0.21714763343334198, -0.05646689981222153, 0.34666818380355835, -0.25391480326652527, 0.11721653491258621, -0.15957418084144592, 0.014043238945305347, 0.02137824147939682, 0.452654629945755, 0.043367691338062286, 0.5742148756980896, 0.0773703008890152, 0.0038449466228485107, -0.020026719197630882, 0.0590364933013916, -0.05646102875471115, 0.08245678246021271, 0.5172518491744995, 0.012443285435438156, -0.3046509921550751, 0.19016331434249878, -0.013954570516943932, 0.15100112557411194, -0.1457110196352005, 0.135862797498703, -0.7447373270988464, -0.16806913912296295, -0.1639159917831421, 0.09809175878763199, 0.18813708424568176, 0.23679706454277039, 0.13399465382099152, 0.02028694935142994, 0.09839169681072235, 0.040643252432346344, -0.20192661881446838, 0.0498930849134922, -0.0115455761551857, -0.12029249966144562, -0.06445655971765518, -0.3988027572631836, -0.004736075643450022, 0.13587115705013275, 0.03781016170978546, -0.14130376279354095, 0.32680103182792664, -0.6951938271522522, 0.029594426974654198, -0.19865041971206665, -0.18865670263767242, 0.07837691158056259, -0.05666445195674896, 0.348881334066391, 0.05260637402534485, 0.031349875032901764, 0.3650309443473816, 0.10654731094837189, 0.09798017144203186, 0.1256767213344574, 0.45802071690559387, 0.2224731147289276, 0.04266718029975891, 0.07235019654035568, 0.030882973223924637, -0.09834778308868408, 0.08075013756752014, 0.1296210139989853, 0.10504904389381409, 0.4748034179210663, 0.044813673943281174, 0.028396079316735268, 0.6129581928253174, -0.05889054387807846, -0.1050395593047142, -0.13506273925304413, 0.08629541099071503, -0.2084171026945114, -0.14418596029281616, -0.7612342238426208, -0.2344602644443512, -0.3558889925479889, 0.1582183837890625, -0.0035039375070482492, -0.5177986025810242, 0.2565993368625641, -0.004544801078736782, -54.14946746826172, 63.574256896972656, -3.1210262775421143, 5.955380916595459, -0.12935924530029297, -0.01398777961730957, -1.3815826260810127e-10, -7.884704000815645e-11, 0.024161411449313164, 0.0, 0.0, 0.0, 0.0, 0.02415470965206623, 3.069528138610611e-14, 1.4904744105592727e-14, 0.0, -9.736084686942995e-16, 0.00010100983490701765, -4.87890977618477e-19, 0.0, -4.718447854656915e-16, -4.87890977618477e-19, 0.00010100983490701765]}, {"packed": [0.00613388093188405, -0.02966710552573204, -0.22711756825447083, -0.2062615305185318, 0.02653047814965248, 0.021234925836324692, -0.10435618460178375, -0.09615787863731384, 0.28351303935050964, 0.8354524970054626, -0.021750828251242638, 0.23100823163986206, -0.0803522914648056, -0.16911928355693817, -0.291553258895874, 0.433957576751709, 0.008098715916275978, 0.31091493368148804, 0.12295275181531906, -0.613599956035614, -0.09476222097873688, -0.4858660101890564, -0.04518047347664833, -0.22827260196208954, -0.18099240958690643, -0.3876033127307892, -0.03156597912311554, 0.05339353531599045, -0.40700238943099976, 0.2012845277786255, 0.10738316923379898, -0.06523136794567108, 0.18482863903045654, -0.08719030022621155, 0.028611307963728905, 0.21566368639469147, -0.10584960132837296, -0.15767928957939148, 0.02884593792259693, 0.6972565054893494, 0.06773491203784943, -0.010825601406395435, -0.05410999432206154, 0.011319488286972046, 0.7273544073104858, -0.11383455991744995, 0.047075167298316956, -0.09791772812604904, 0.09704864025115967, 0.01958605647087097, -0.40045323967933655, 0.23400375247001648, 0.28061240911483765, 0.009221521206200123, -0.13593491911888123, -0.00911293737590313, -0.20352838933467865, -0.07237205654382706, -0.02479838952422142, -0.07209012657403946, 0.1305071860551834, -0.4246126115322113, 0.06189333274960518, 0.009577939286828041, 0.16295389831066132, -0.12356125563383102, 0.05854427069425583, -0.28985780477523804, -0.2520991861820221, -0.1986776888370514, 0.2403799146413803, 0.27612894773483276, -0.08986365795135498, 0.19882117211818695, 0.049873027950525284, 0.6201731562614441, 0.023285482078790665, -0.167131707072258, 0.0032012390438467264, -0.04697422310709953, 0.1279377043247223, 0.552155613899231, -0.21433576941490173, 0.4468078017234802, -0.05261501297354698, 0.14788952469825745, 0.05538061633706093, 0.3644789755344391, -0.2336539626121521, -0.0013093823799863458, 0.03934543952345848, -0.11778946220874786, 0.058415114879608154, 0.015572807751595974, 0.010523958131670952, 0.05012335628271103, 0.08945726603269577, 0.4049820303916931, -0.25709226727485657, -0.048480886965990067, 0.1989588588476181, 0.29130497574806213, 0.1836431324481964, -0.09874846786260605, 0.03564772009849548, 0.09272709488868713, -0.05785660818219185, 0.24970027804374695, 0.04351602494716644, -0.40719372034072876, 0.36565133929252625, -0.10547897219657898, 0.31718459725379944, 0.2450810670852661, 0.09223587810993195, 0.008751928806304932, -0.14311319589614868, 0.061550118029117584, -0.17173290252685547, 0.47528979182243347, -0.37231534719467163, -0.37899553775787354, -0.36375313997268677, 0.2465224266052246, 0.028031008318066597, -0.297299861907959, 0.12680241465568542, 0.05196281522512436, -15.289440155029297, -0.8162155151367188, 3.0886900424957275, 8.267921447753906, -0.07386493682861328, -0.008397459983825684, -1.3815826260810127e-10, -7.884704000815645e-11, 0.024161411449313164, 0.0, 0.0, 0.0, 0.0, 0.024161411449313164, -4.8691519566324e-16, -2.3592239273284576e-16, 0.0, -4.868042343471497e-16, 0.00010100983490701765, -4.87890977618477e-19, 0.0, -2.3592239273284576e-16, -4.87890977618477e-19, 0.00010100983490701765]}, {"packed": [0.01866081915795803, -0.10753091424703598, 0.27368518710136414, -0.25402095913887024, -0.2732182741165161, 0.16510261595249176, 0.13736945390701294, 0.12134654819965363, 0.06957940012216568, 0.7026154398918152, -0.12641261518001556, -0.013992974534630775, -0.22761781513690948, -0.01797761581838131, 0.15670143067836761, -0.0384695865213871, 0.051563143730163574, 0.14899547398090363, 0.0995623990893364, -0.5334678292274475, -0.03572481498122215, -0.22920162975788116, -0.1710924506187439, 0.038536328822374344, -0.24197950959205627, 0.08297097682952881, -0.2790053188800812, 0.17341968417167664, -0.13827897608280182, 0.1403280347585678, 0.045881640166044235, -0.14703860878944397, -0.25678861141204834, -0.18585383892059326, 0.31107890605926514, 0.021268054842948914, -0.13821041584014893, 0.08832894265651703, 0.01382908970117569, -0.022993147373199463, 0.1328156441450119, 0.021731212735176086, -0.16841666400432587, 0.03772793337702751, 0.38000473380088806, -0.11860910803079605, 0.13093848526477814, -0.1378255933523178, -0.013435758650302887, -0.022860005497932434, 0.38882049918174744, -0.00036092978552915156, -0.14566917717456818, 0.0643417090177536, -0.04261791706085205, -0.012260271236300468, -0.1953275501728058, -0.13486288487911224, 0.03410510718822479, 0.345223069190979, 0.09909164905548096, -0.24099129438400269, 0.13553227484226227, -0.07694690674543381, -0.16084778308868408, -0.10549402236938477, -0.13572029769420624, -0.17229938507080078, -0.20618116855621338, -0.23075483739376068, 0.029292568564414978, 0.153362438082695, 0.01600458286702633, 0.2612350881099701, 0.020000034943223, 0.12960313260555267, -0.02245280146598816, -0.25698426365852356, 0.11583811044692993, 0.0200115405023098, 0.029947208240628242, 0.44821733236312866, -0.2917286157608032, -0.027839872986078262, -0.2111501693725586, 0.02197183482348919, -0.05540047958493233, 0.2252967804670334, -0.28382518887519836, -0.010919305495917797, 0.05470053106546402, -0.15394994616508484, 0.07253067940473557, -0.03907566890120506, 0.3534916043281555, 0.07806780189275742, 0.04524921625852585, 0.2498999983072281, -0.10817287862300873, 0.0010113301686942577, 0.28025946021080017, 0.21501792967319489, 0.14512847363948822, 0.051469672471284866, 0.165805384516716, -0.036239489912986755, -0.06121641770005226, 0.06078580394387245, -0.06632011383771896, -0.3016221523284912, 0.6134962439537048, 0.08778220415115356, 0.0032580895349383354, 0.051894064992666245, 0.056416645646095276, -0.09296382963657379, -0.24842344224452972, 0.08184188604354858, -0.17024065554141998, 0.256765216588974, -0.7045985460281372, -0.3809143304824829, -0.2542717456817627, 0.20292484760284424, -0.004704427905380726, -0.5088404417037964, 0.21115823090076447, -0.10464209318161011, -49.464759826660156, -0.29775238037109375, 3.0822818279266357, 7.474017143249512, -0.17018508911132812, -0.005147814750671387, -1.3815826260810127e-10, -7.884704000815645e-11, 0.024161411449313164, 0.0, 0.0, 0.0, 0.0, 0.024161411449313164, -2.573353856394345e-16, -1.249000902703301e-16, 0.0, -2.572799049813893e-16, 0.00010100983490701765, -4.87890977618477e-19, 0.0, -1.249000902703301e-16, -4.87890977618477e-19, 0.00010100983490701765]}, {"packed": [-0.004389416892081499, -0.07615651935338974, -0.2456595003604889, -0.08184779435396194, -0.03133290633559227, -0.026062576100230217, -0.02193475142121315, 0.07634036242961884, -0.15042753517627716, -0.043340928852558136, 0.08727692067623138, 0.19077932834625244, 0.042477674782276154, 0.13096509873867035, -0.15025261044502258, 0.0071474285796284676, 0.0324266217648983, 0.3380347788333893, 0.15583378076553345, -0.7840956449508667, -0.034952204674482346, -0.09985855221748352, 0.09763684868812561, 0.18217578530311584, 0.11212176829576492, 0.00031827727798372507, 0.023158686235547066, 0.019209612160921097, -0.07202110439538956, -0.011938957497477531, -0.011965639889240265, -0.15408913791179657, 0.05647780001163483, 0.20174579322338104, 0.16313891112804413, 0.18567237257957458, -0.11810778826475143, -0.05499544367194176, 0.030590157955884933, -0.14357031881809235, -0.0008776827598921955, -0.08095097541809082, -0.14603640139102936, -0.09317602962255478, -0.04413869231939316, -0.628239095211029, -0.35150405764579773, 0.007344256155192852, 0.1543794870376587, 0.007725118193775415, -0.12069489806890488, -0.019369177520275116, 0.9220451712608337, 0.011874138377606869, -0.06493571400642395, -0.046064265072345734, -0.016517918556928635, -0.0920201763510704, -0.019478201866149902, 0.449381947517395, 0.12808692455291748, -0.14567211270332336, 0.05282074585556984, 0.2389242947101593, 0.2355954945087433, -0.20173989236354828, 0.18781131505966187, -0.6219390034675598, -0.11806230992078781, 0.053893834352493286, 0.1284342110157013, 0.14877387881278992, 0.31463930010795593, -0.11943615227937698, 0.017671819776296616, 0.013185141608119011, 0.051377132534980774, -0.11262430995702744, -0.1253616362810135, 0.03139491379261017, -0.10410847514867783, -0.21293765306472778, -0.3552570641040802, 0.3008866608142853, 0.2981169521808624, 0.05496232584118843, 0.14655044674873352, 0.23025855422019958, -0.6018280982971191, 0.08188353478908539, -0.16797661781311035, -0.2535041570663452, 0.17769324779510498, -0.10359087586402893, 0.07352612167596817, 0.05721723660826683, 0.07926177233457565, 0.20594973862171173, 0.2903633713722229, 0.24169223010540009, -0.465513676404953, 0.42337554693222046, 0.24980521202087402, -0.14983125030994415, 0.04286067932844162, 0.13127560913562775, -0.16966748237609863, 0.08243589848279953, 0.2786659598350525, 0.28402239084243774, 0.2771575450897217, -0.14372773468494415, 0.11399748176336288, 0.6632423400878906, -0.1407587081193924, 0.018537895753979683, -0.33567628264427185, 0.1119350790977478, -0.14472731947898865, -0.1539432555437088, -0.6785349249839783, -0.11721183359622955, -0.3939192593097687, 0.2075234055519104, -0.014828653074800968, -0.6845215559005737, 0.20214030146598816, 0.18962475657463074, -56.844173431396484, 60.394920349121094, 0.1337735652923584, 6.314300060272217, -0.007620096206665039, -0.021609783172607422, -1.3815826260810127e-10, -7.884704000815645e-11, 0.024161411449313164, 0.0, 0.0, 0.0, 0.0, 0.02415470965206623, 3.069528138610611e-14, 1.4904744105592727e-14, 0.0, -9.736084686942995e-16, 0.00010100983490701765, -4.87890977618477e-19, 0.0, -4.718447854656915e-16, -4.87890977618477e-19, 0.00010100983490701765]}]}